{
  "root_id": 0,
  "paths": {
    "paths": [
      [
        0,
        {
          "crate_id": null,
          "path": "kind_change_old",
          "span": {
            "filename": "fixtures/kind_change/old/src/lib.rs",
            "begin": [
              1,
              0
            ],
            "end": [
              1,
              15
            ]
          },
          "item_id": null,
          "children": [
            1
          ]
        }
      ],
      [
        1,
        {
          "crate_id": null,
          "path": "kind_change_old::Abc",
          "span": {
            "filename": "fixtures/kind_change/old/src/lib.rs",
            "begin": [
              1,
              0
            ],
            "end": [
              1,
              15
            ]
          },
          "item_id": 0,
          "children": []
        }
      ]
    ]
  },
  "items": {
    "items": [
      [
        0,
        {
          "crate_id": null,
          "name": "Abc",
          "span": {
            "filename": "fixtures/kind_change/old/src/lib.rs",
            "begin": [
              1,
              0
            ],
            "end": [
              1,
              15
            ]
          }
        }
      ]
    ]
  },
  "crates": {
    "crates": []
  }
}