{
  "root_id": 0,
  "paths": {
    "paths": [
      [
        0,
        {
          "crate_id": null,
          "path": "removal_use_new",
          "span": {
            "filename": "fixtures/removal_use/new/src/lib.rs",
            "begin": [
              1,
              0
            ],
            "end": [
              4,
              1
            ]
          },
          "item_id": null,
          "children": [
            1
          ]
        }
      ],
      [
        1,
        {
          "crate_id": null,
          "path": "removal_use_new::Def",
          "span": {
            "filename": "fixtures/removal_use/new/src/lib.rs",
            "begin": [
              1,
              0
            ],
            "end": [
              4,
              1
            ]
          },
          "item_id": 0,
          "children": []
        }
      ]
    ]
  },
  "items": {
    "items": [
      [
        0,
        {
          "crate_id": null,
          "name": "Def",
          "span": {
            "filename": "fixtures/removal_use/new/src/lib.rs",
            "begin": [
              1,
              0
            ],
            "end": [
              4,
              1
            ]
          }
        }
      ]
    ]
  },
  "crates": {
    "crates": []
  }
}